qqpusher/__init__.py
qqpusher-0.1.7.dist-info/LICENSE
qqpusher-0.1.7.dist-info/METADATA
qqpusher-0.1.7.dist-info/WHEEL
qqpusher-0.1.7.dist-info/top_level.txt
qqpusher-0.1.7.dist-info/RECORD
