Metadata-Version: 2.1
Name: qqpusher
Version: 0.1.7
Summary: SDK for qqpusher
Home-page: https://github.com/Qualthera/qqpusher.git
Author: Qualthera
Author-email: qualthera@163.com
License: GPLv3
Platform: all
Classifier: Programming Language :: Python :: 3
Classifier: License :: OSI Approved :: GNU General Public License v3 (GPLv3)
Classifier: Operating System :: OS Independent
Requires-Dist: requests (>=2.25.0)
